23igeg-0.1.3.dist-info/licenses/LICENSE
igeg/__init__.py
igeg/logger.py
23igeg-0.1.3.dist-info/METADATA
23igeg-0.1.3.dist-info/WHEEL
23igeg-0.1.3.dist-info/top_level.txt
23igeg-0.1.3.dist-info/RECORD
