Metadata-Version: 2.4
Name: 23igeg
Version: 0.1.3
Summary: Libreria dimostrativa di keylogging per progetti di sicurezza informatica
Home-page: https://github.com/tuo-user/23igeg
Author: Il Tuo Nome
Classifier: Programming Language :: Python :: 3
Classifier: Topic :: Security
Classifier: License :: OSI Approved :: MIT License
Classifier: Intended Audience :: Education
Requires-Python: >=3.6
License-File: LICENSE
Requires-Dist: pynput
Dynamic: author
Dynamic: classifier
Dynamic: description
Dynamic: description-content-type
Dynamic: home-page
Dynamic: license-file
Dynamic: requires-dist
Dynamic: requires-python
Dynamic: summary
